equitext.py
equitext-1.dist-info/DESCRIPTION.rst
equitext-1.dist-info/METADATA
equitext-1.dist-info/RECORD
equitext-1.dist-info/WHEEL
equitext-1.dist-info/metadata.json
equitext-1.dist-info/top_level.txt
