Metadata-Version: 2.0
Name: equitext
Version: 1
Summary: A text-to-text encoding. Characters have the same number of occurences in the encoded text
Home-page: https://github.com/foobuzz/equitext
Author: foobuzz
Author-email: dprosium@gmail.com
License: UNKNOWN
Keywords: encoding text character occurence frequency
Platform: UNKNOWN
